{"type":"FeatureCollection","features":[{"type":"Feature","properties":{"id":1100000129,"stream":"Boivin Creek","utm_zone":11,"utm_easting":647275,"utm_northing":5541987,"dbm_mof_50k_grid":"082J.103","barrier_ind":"F","Notes":"Remnant dam not located in main channel.","name":"tab_dams_raw"},"geometry":{"type":"Point","coordinates":[-114.9444246,50.0119779]}},{"type":"Feature","properties":{"id":1100002016,"stream":"Harmer Creek","utm_zone":11,"utm_easting":657051,"utm_northing":5522119,"dbm_mof_50k_grid":"082G.123","barrier_ind":"T","Notes":"Large dam (15m  high at 55% grade) located in main channel. No fish ladder.","name":"tab_dams_raw"},"geometry":{"type":"Point","coordinates":[-114.8161642,49.8309156]}},{"type":"Feature","properties":{"id":197542,"stream":"Hartley Creek","utm_zone":11,"utm_easting":643537,"utm_northing":5490723,"dbm_mof_50k_grid":"082G.113","barrier_ind":"T","Notes":"Two small dams (30cm and 40cm high) located just upstream (7m and 20m) of Dicken Road. Likely easily passable by adult WCT but barrier to fry and small juveniles. If culvert replaces these could be fixed concurrently.","name":"tab_dams_raw"},"geometry":{"type":"Point","coordinates":[-115.0154831,49.5520811]}}]}